openedx_course_enrollment_audit/__init__.py
openedx_course_enrollment_audit/apps.py
openedx_course_enrollment_audit/compat.py
openedx_course_enrollment_audit/models.py
openedx_course_enrollment_audit/signals.py
openedx_course_enrollment_audit/management/__init__.py
openedx_course_enrollment_audit/management/commands/__init__.py
openedx_course_enrollment_audit/management/commands/backfill_course_enrollment_audit.py
openedx_course_enrollment_audit/migrations/0001_initial.py
openedx_course_enrollment_audit/migrations/__init__.py
openedx_course_enrollment_audit-1.0.1.dist-info/licenses/LICENSE.txt
openedx_course_enrollment_audit-1.0.1.dist-info/METADATA
openedx_course_enrollment_audit-1.0.1.dist-info/WHEEL
openedx_course_enrollment_audit-1.0.1.dist-info/entry_points.txt
openedx_course_enrollment_audit-1.0.1.dist-info/top_level.txt
openedx_course_enrollment_audit-1.0.1.dist-info/RECORD
